my_math/__init__.py
my_math/operations.py
structureddataXX-0.0.2.dist-info/LICENSE.txt
structureddataXX-0.0.2.dist-info/METADATA
structureddataXX-0.0.2.dist-info/WHEEL
structureddataXX-0.0.2.dist-info/top_level.txt
structureddataXX-0.0.2.dist-info/RECORD
